iiyo/__init__.py
iiyo/art/__init__.py
iiyo/colombo/__init__.py
iiyo/english_names/__init__.py
iiyo/english_names/dist.all.py
iiyo/english_names/dist.female.py
iiyo/english_names/dist.male.py
iiyo/random_names/__init__.py
iiyo/random_names/city.py
iiyo/random_names/female_first_names.py
iiyo/random_names/home_address.py
iiyo/random_names/last_names.py
iiyo/random_names/male_first_names.py
iiyo/random_names/name.py
iiyo/sinhala/Data.py
iiyo/sinhala/__init__.py
iiyo-1.0.7.dist-info/LICENCE.txt
iiyo-1.0.7.dist-info/METADATA
iiyo-1.0.7.dist-info/WHEEL
iiyo-1.0.7.dist-info/top_level.txt
iiyo-1.0.7.dist-info/RECORD
